tencentcloud/__init__.py
tencentcloud/mgobe/__init__.py
tencentcloud/mgobe/v20190929/__init__.py
tencentcloud/mgobe/v20190929/errorcodes.py
tencentcloud/mgobe/v20190929/mgobe_client.py
tencentcloud/mgobe/v20190929/models.py
tencentcloud/mgobe/v20201014/__init__.py
tencentcloud/mgobe/v20201014/errorcodes.py
tencentcloud/mgobe/v20201014/mgobe_client.py
tencentcloud/mgobe/v20201014/models.py
tencentcloud_sdk_python_mgobe-3.0.1416.dist-info/METADATA
tencentcloud_sdk_python_mgobe-3.0.1416.dist-info/WHEEL
tencentcloud_sdk_python_mgobe-3.0.1416.dist-info/top_level.txt
tencentcloud_sdk_python_mgobe-3.0.1416.dist-info/RECORD
